imf/__init__.py
imf-0.0.1a0.dist-info/LICENSE
imf-0.0.1a0.dist-info/WHEEL
imf-0.0.1a0.dist-info/METADATA
imf-0.0.1a0.dist-info/RECORD
