Metadata-Version: 2.1
Name: imf
Version: 0.0.1a0
Summary: Pythonic API access to IMF data - Unofficial
Home-page: https://github.com/nathanbegbie/imf
License: MIT
Keywords: imf,REST API
Author: nathanbegbie
Author-email: nathanbegbie@gmail.com
Requires-Python: >=3.7,<4.0
Classifier: License :: OSI Approved :: MIT License
Classifier: Programming Language :: Python :: 3
Classifier: Programming Language :: Python :: 3.7
Classifier: Programming Language :: Python :: 3.8
Requires-Dist: requests (>=2.23.0,<3.0.0)
Project-URL: Repository, https://github.com/nathanbegbie/imf
